[{"create-time":1614352709797,"title":"programmable feeds slide",":create/user":{":user/uid":"ZP6qOGnCTgS3uoT30U1tRsUxUVv2"},"children":[{"string":"Title","create-time":1614352711789,":create/user":{":user/uid":"ZP6qOGnCTgS3uoT30U1tRsUxUVv2"},"children":[{"string":"Programmable Feeds","create-time":1614352713217,"uid":"D7pt5BNZu","edit-time":1614352720058,":create/user":{":user/uid":"ZP6qOGnCTgS3uoT30U1tRsUxUVv2"},":edit/user":{":user/uid":"ZP6qOGnCTgS3uoT30U1tRsUxUVv2"}}],"uid":"N_lPzLi54","edit-time":1614352711789,":edit/user":{":user/uid":"ZP6qOGnCTgS3uoT30U1tRsUxUVv2"}},{"string":"Description","create-time":1614352713217,":create/user":{":user/uid":"ZP6qOGnCTgS3uoT30U1tRsUxUVv2"},"children":[{"string":"","create-time":1614352713217,"uid":"Qkhpk7itu","edit-time":1614352713217,":create/user":{":user/uid":"ZP6qOGnCTgS3uoT30U1tRsUxUVv2"},":edit/user":{":user/uid":"ZP6qOGnCTgS3uoT30U1tRsUxUVv2"}}],"uid":"iitxKmGyf","edit-time":1614352713217,":edit/user":{":user/uid":"ZP6qOGnCTgS3uoT30U1tRsUxUVv2"}},{"string":"Body","create-time":1614352713217,":create/user":{":user/uid":"ZP6qOGnCTgS3uoT30U1tRsUxUVv2"},"children":[{"string":"![](https://firebasestorage.googleapis.com/v0/b/firescript-577a2.appspot.com/o/imgs%2Fapp%2FVerso%2FQjlD48rIS7.png?alt=media&token=1a29364c-8c15-4a7d-87a4-49221e00bb8f)","uid":"VPK-PzyXA","edit-time":1614352726397,":edit/user":{":user/uid":"ZP6qOGnCTgS3uoT30U1tRsUxUVv2"}},{"string":"","create-time":1614352713217,"uid":"1SRvy0iRX","edit-time":1614352713217,":create/user":{":user/uid":"ZP6qOGnCTgS3uoT30U1tRsUxUVv2"},":edit/user":{":user/uid":"ZP6qOGnCTgS3uoT30U1tRsUxUVv2"}}],"uid":"bUB2RONHn","edit-time":1614352713217,":edit/user":{":user/uid":"ZP6qOGnCTgS3uoT30U1tRsUxUVv2"}}],"uid":"lvfB4SQUV","edit-time":1614352709797,":edit/user":{":user/uid":"ZP6qOGnCTgS3uoT30U1tRsUxUVv2"}}]